epub2html/__init__.py
epub2html/__main__.py
epub2html/epub2html.py
epub2html/jquery.min.js
epub2html/leader-line.min.js
epub2html/template.html
epub2html-2.2.41.dist-info/METADATA
epub2html-2.2.41.dist-info/WHEEL
epub2html-2.2.41.dist-info/entry_points.txt
epub2html-2.2.41.dist-info/top_level.txt
epub2html-2.2.41.dist-info/RECORD
