Metadata-Version: 2.1
Name: epub2html
Version: 2.2.41
Summary: this is a description
Home-page: https://github.com/zk4/epub2html
Download-URL: https://github.com/zk4/epub2html/archive/master.zip
Author: zk
Author-email: liuzq7@gmail.com
License: BSD
Keywords: best practice for python project
Classifier: Development Status :: 5 - Production/Stable
Classifier: Environment :: Console
Requires-Python: >3.0.0
Requires-Dist: lxml (==4.9.2)
Requires-Dist: xmltodict (==0.13.0)
